niripwmenu/__init__.py
niripwmenu/click.py
niripwmenu/config.py
niripwmenu/constants.py
niripwmenu/util.py
niripwmenu/window.py
niripwmenu/assets/banner.jpg
niripwmenu/assets/config.yaml
niripwmenu/assets/logoff.png
niripwmenu/assets/reboot.png
niripwmenu/assets/shutdown.png
niripwmenu/assets/style.css
niripwmenu-0.1.4.dist-info/METADATA
niripwmenu-0.1.4.dist-info/WHEEL
niripwmenu-0.1.4.dist-info/entry_points.txt
niripwmenu-0.1.4.dist-info/licenses/LICENSE
niripwmenu-0.1.4.dist-info/RECORD
