Metadata-Version: 2.4
Name: niripwmenu
Version: 0.1.4
Summary: A modern powermenu for Niri Scrollable-Tiling Wayland compositor.
Project-URL: homepage, https://github.com/AntraXClown/niripwmenu
Project-URL: Repository, https://github.com/AntraXClown/niripwmenu
Author-email: Antrax <fredcox@gmail.com>
License: MIT
License-File: LICENSE
Requires-Python: >=3.13
Requires-Dist: confz>=2.1.0
Requires-Dist: pygobject-stubs>=2.13.0
Requires-Dist: pygobject>=3.52.3
Requires-Dist: rich>=14.0.0
